CensusForge/CensusForge.py
CensusForge/__init__.py
CensusForge/database.db
CensusForge/utils.py
censusforge-0.5.1.dist-info/METADATA
censusforge-0.5.1.dist-info/WHEEL
censusforge-0.5.1.dist-info/entry_points.txt
censusforge-0.5.1.dist-info/licenses/LICENSE
censusforge-0.5.1.dist-info/RECORD
