Metadata-Version: 2.4
Name: CensusForge
Version: 0.5.1
Summary: Add your description here
Author-email: Alejandro Ouslan <alejandro.ouslan@upr.edu>
License-File: LICENSE
Requires-Python: >=3.12
Requires-Dist: duckdb>=1.4.2
Requires-Dist: jp-tools>=0.3.4
Requires-Dist: numpy>=2.4.0
Requires-Dist: requests>=2.32.5
Requires-Dist: setuptools>=80.9.0
Provides-Extra: extra
Requires-Dist: geopandas>=1.1.2; extra == 'extra'
